MDPOW-0.9.0.data/scripts/mdpow-cfg2yaml.py
MDPOW-0.9.0.data/scripts/mdpow-check
MDPOW-0.9.0.data/scripts/mdpow-equilibrium
MDPOW-0.9.0.data/scripts/mdpow-fep
MDPOW-0.9.0.data/scripts/mdpow-get-runinput
MDPOW-0.9.0.data/scripts/mdpow-pcw
MDPOW-0.9.0.data/scripts/mdpow-pow
MDPOW-0.9.0.data/scripts/mdpow-ptw
MDPOW-0.9.0.data/scripts/mdpow-rebuild-fep
MDPOW-0.9.0.data/scripts/mdpow-rebuild-simulation
MDPOW-0.9.0.data/scripts/mdpow-solvationenergy
mdpow/__init__.py
mdpow/_version.py
mdpow/config.py
mdpow/equil.py
mdpow/fep.py
mdpow/filelock.py
mdpow/forcefields.py
mdpow/log.py
mdpow/restart.py
mdpow/run.py
mdpow/analysis/__init__.py
mdpow/analysis/dihedral.py
mdpow/analysis/ensemble.py
mdpow/analysis/solvation.py
mdpow/templates/NPT_amber.mdp
mdpow/templates/NPT_charmm.mdp
mdpow/templates/NPT_opls.mdp
mdpow/templates/bar_amber.mdp
mdpow/templates/bar_charmm.mdp
mdpow/templates/bar_opls.mdp
mdpow/templates/em_amber.mdp
mdpow/templates/em_charmm.mdp
mdpow/templates/em_opls.mdp
mdpow/templates/runinput.yml
mdpow/templates/system.top.template
mdpow/templates/system_octwet.top.template
mdpow/tests/__init__.py
mdpow/tests/tempdir.py
mdpow/tests/test_Gsolv.py
mdpow/tests/test_analysis.py
mdpow/tests/test_analysis_alchemlyb.py
mdpow/tests/test_automated_dihedral_analysis.py
mdpow/tests/test_config.py
mdpow/tests/test_dihedral.py
mdpow/tests/test_ensemble.py
mdpow/tests/test_equilibration_script.py
mdpow/tests/test_fep.py
mdpow/tests/test_fep_analysis.py
mdpow/tests/test_fep_script.py
mdpow/tests/test_filelock.py
mdpow/tests/test_forcefields.py
mdpow/tests/test_journals.py
mdpow/tests/test_run.py
mdpow/tests/test_runinput.py
mdpow/tests/test_solv_shell.py
mdpow/tests/test_solvation.py
mdpow/tests/test_version.py
mdpow/tests/test_workflows_base.py
mdpow/tests/test_workflows_registry.py
mdpow/top/1cyclo.gro
mdpow/top/1cyclo_amber.gro
mdpow/top/1cyclo_charmm.gro
mdpow/top/1oct.gro
mdpow/top/1oct_amber.gro
mdpow/top/1oct_charmm.gro
mdpow/top/1octwet.gro
mdpow/top/1octwet_amber.gro
MDPOW-0.9.0.dist-info/AUTHORS
MDPOW-0.9.0.dist-info/COPYING
MDPOW-0.9.0.dist-info/METADATA
MDPOW-0.9.0.dist-info/WHEEL
MDPOW-0.9.0.dist-info/top_level.txt
MDPOW-0.9.0.dist-info/zip-safe
MDPOW-0.9.0.dist-info/RECORD
