Metadata-Version: 2.1
Name: MDPOW
Version: 0.9.0
Summary: A library for computing solvation/water partitioning coefficients using molecular dynamics simulations
Home-page: https://github.com/Becksteinlab/MDPOW
Author: Oliver Beckstein
Author-email: orbeckst@gmail.com
License: GPLv3
Keywords: science Gromacs analysis 'molecular dynamics'
Classifier: Development Status :: 4 - Beta
Classifier: Environment :: Console
Classifier: Intended Audience :: Science/Research
Classifier: License :: OSI Approved :: GNU General Public License v3 or later (GPLv3+)
Classifier: Operating System :: POSIX
Classifier: Operating System :: MacOS :: MacOS X
Classifier: Programming Language :: Python
Classifier: Programming Language :: Python :: 3
Classifier: Programming Language :: Python :: 3.10
Classifier: Programming Language :: Python :: 3.11
Classifier: Programming Language :: Python :: 3.12
Classifier: Topic :: Scientific/Engineering :: Chemistry
Classifier: Topic :: Scientific/Engineering :: Physics
License-File: COPYING
License-File: AUTHORS
Requires-Dist: numpy >=1.6
Requires-Dist: scipy >=1.11.0
Requires-Dist: pyyaml
Requires-Dist: GromacsWrapper >=0.5.1
Requires-Dist: numkit
Requires-Dist: six
Requires-Dist: mdanalysis >=2
Requires-Dist: alchemlyb >=2
Requires-Dist: pandas
Requires-Dist: pymbar >=4
Requires-Dist: matplotlib
Requires-Dist: seaborn
Requires-Dist: rdkit
Requires-Dist: svgutils
Requires-Dist: cairosvg
Requires-Dist: pypdf
